cloudns_api/__init__.py
cloudns_api/api.py
cloudns_api/config.py
cloudns_api/parameters.py
cloudns_api/record.py
cloudns_api/soa.py
cloudns_api/validation.py
cloudns_api/zone.py
tests/__init__.py
tests/conftest.py
tests/helpers.py
tests/test_api.py
tests/test_parameters.py
tests/test_record.py
tests/test_soa.py
tests/test_validation.py
tests/test_zone.py
cloudns_api-0.9.6.dist-info/LICENSE
cloudns_api-0.9.6.dist-info/METADATA
cloudns_api-0.9.6.dist-info/WHEEL
cloudns_api-0.9.6.dist-info/top_level.txt
cloudns_api-0.9.6.dist-info/RECORD
