Metadata-Version: 2.1
Name: cloudns-api
Version: 0.9.6
Summary: A python interface to the ClouDNS.net API
Home-page: https://github.com/prestix-studio/cloudns_api
Author: Harold Bradley III | Prestix Studio, LLC
Author-email: harold@prestix.studio
License: MIT License
Download-URL: https://github.com/prestix-studio/cloudns_api/archive/v0.9.6.tar.gz
Keywords: dns,dns api,domain name system,cloudns,server development
Platform: UNKNOWN
Classifier: Development Status :: 4 - Beta
Classifier: Intended Audience :: Developers
Classifier: Topic :: Software Development :: Build Tools
Classifier: License :: OSI Approved :: MIT License
Classifier: Programming Language :: Python :: 3.5
Classifier: Programming Language :: Python :: 3.6
Requires-Python: >3.5
Requires-Dist: requests
